{
  "id": "00000000-0000-0000-0000-000000000000",
  "schemaVersion": "models.meshery.io/v1beta1",
  "version": "v1.0.0",
  "name": "vmware-tanzu",
  "displayName": "Vmware Tanzu",
  "status": "ignored",
  "registrant": {
    "id": "00000000-0000-0000-0000-000000000000",
    "name": "Artifact Hub",
    "credential_id": "00000000-0000-0000-0000-000000000000",
    "type": "registry",
    "sub_type": "",
    "kind": "artifacthub",
    "status": "discovered",
    "user_id": "00000000-0000-0000-0000-000000000000",
    "created_at": "0001-01-01T00:00:00Z",
    "updated_at": "0001-01-01T00:00:00Z",
    "deleted_at": "0001-01-01T00:00:00Z"
  },
  "connection_id": "00000000-0000-0000-0000-000000000000",
  "category": {
    "id": "00000000-0000-0000-0000-000000000000",
    "name": "Orchestration \u0026 Management"
  },
  "subCategory": "Certified Kubernetes - Distribution",
  "metadata": {
    "capabilities": null,
    "isAnnotation": false,
    "primaryColor": "#00B39F",
    "secondaryColor": "#00D3A9",
    "shape": "circle",
    "styleOverrides": "",
    "svgColor": "",
    "svgComplete": "",
    "svgWhite": ""
  },
  "model": {
    "version": "9.0.3"
  },
  "components_count": 0,
  "relationships_count": 0,
  "components": null,
  "relationships": null
}