{"kind":"WorkloadEntry","apiVersion":"v1alpha3","display-name":"Workload Entry","format":"JSON","metadata":{},"model":{"name":"kubeflow","version":"1.5.1","display-name":"","category":"","sub-category":""},"schema":"{\n \"description\": \"Configuration affecting VMs onboarded into the mesh. See more details at: https://istio.io/docs/reference/config/networking/workload-entry.html\",\n \"properties\": {\n  \"address\": {\n   \"type\": \"string\"\n  },\n  \"labels\": {\n   \"additionalProperties\": {\n    \"type\": \"string\"\n   },\n   \"description\": \"One or more labels associated with the endpoint.\",\n   \"type\": \"object\"\n  },\n  \"locality\": {\n   \"description\": \"The locality associated with the endpoint.\",\n   \"type\": \"string\"\n  },\n  \"network\": {\n   \"type\": \"string\"\n  },\n  \"ports\": {\n   \"additionalProperties\": {\n    \"type\": \"integer\"\n   },\n   \"description\": \"Set of ports associated with the endpoint.\",\n   \"type\": \"object\"\n  },\n  \"serviceAccount\": {\n   \"type\": \"string\"\n  },\n  \"weight\": {\n   \"description\": \"The load balancing weight associated with the endpoint.\",\n   \"type\": \"integer\"\n  }\n },\n \"title\": \"Workload Entry\",\n \"type\": \"object\"\n}"}