{"kind":"TridentOrchestrator","apiVersion":"trident.netapp.io/v1","displayName":"Trident Orchestrator","format":"JSON","hostname":"","hostID":"00000000-0000-0000-0000-000000000000","displayhostname":"","metadata":{"isNamespaced":false},"model":{"name":"trident-operator","version":"23.1.1","displayName":"trident-operator","hostname":"","hostID":"00000000-0000-0000-0000-000000000000","displayhostname":"","category":{"name":"","metadata":null},"metadata":{"source_uri":"https://netapp.github.io/trident-helm-chart/charts/trident-operator-23.10.0.tgz"}},"schema":"{\n \"title\": \"Trident Orchestrator\",\n \"type\": \"object\",\n \"x-kubernetes-preserve-unknown-fields\": true\n}"}